jittermodel/__init__.py
jittermodel/_sim.so
jittermodel/_version.py
jittermodel/base.py
jittermodel/plot.py
jittermodel/simulation.py
jittermodel/tests/__init__.py
jittermodel/tests/scratchwork.py
jittermodel/tests/test__init__.py
jittermodel/tests/test_base.py
jittermodel/tests/test_plot.py
jittermodel/tests/test_simulation.py
jittermodel/tests/time_execution.py
jittermodel-0.2.3.dist-info/DESCRIPTION.rst
jittermodel-0.2.3.dist-info/METADATA
jittermodel-0.2.3.dist-info/metadata.json
jittermodel-0.2.3.dist-info/RECORD
jittermodel-0.2.3.dist-info/top_level.txt
jittermodel-0.2.3.dist-info/WHEEL
