Metadata-Version: 2.0
Name: jittermodel
Version: 0.2.3
Summary: Calculate jitter and non-contact friction for an AFM cantilever
Home-page: http://github.com/ryanpdwyer/jittermodel
Author: Ryan Dwyer
Author-email: ryanpdwyer@gmail.com
License: MIT
Platform: UNKNOWN
Classifier: Development Status :: 3 - Alpha
Classifier: Intended Audience :: Science/Research
Classifier: License :: OSI Approved :: MIT License
Classifier: Operating System :: MacOS :: MacOS X
Classifier: Operating System :: Microsoft :: Windows
Classifier: Operating System :: POSIX
Classifier: Topic :: Scientific/Engineering
Classifier: Programming Language :: Python :: 2
Classifier: Programming Language :: Python :: 2.7
Requires-Dist: numpy
Requires-Dist: scipy
Requires-Dist: matplotlib
Requires-Dist: pint
Provides-Extra: dev
Requires-Dist: sphinx; extra == 'dev'
